hy_fancy_repl/__init__.py
hy_fancy_repl/__main__.py
hy_fancy_repl/repl.py
hy_fancy_repl-1.2.0.dist-info/licenses/AUTHORS
hy_fancy_repl-1.2.0.dist-info/licenses/LICENSE
hy_fancy_repl-1.2.0.dist-info/METADATA
hy_fancy_repl-1.2.0.dist-info/WHEEL
hy_fancy_repl-1.2.0.dist-info/entry_points.txt
hy_fancy_repl-1.2.0.dist-info/top_level.txt
hy_fancy_repl-1.2.0.dist-info/RECORD
