Metadata-Version: 2.4
Name: hy-fancy-repl
Version: 1.2.0
Summary: A fancy Hy REPL.
Author-email: Ati Sharma <ati+hy-fancy-repl@agalmic.ltd>
License: MIT License
Project-URL: Repository, https://github.com/atisharma/hy-fancy-repl
Keywords: hy,hylang,utilities,repl
Classifier: License :: OSI Approved :: MIT License
Classifier: Programming Language :: Python :: 3
Classifier: Programming Language :: Python :: 3.13
Classifier: Programming Language :: Python :: 3.14
Classifier: Programming Language :: Lisp
Classifier: Programming Language :: Hy
Classifier: Environment :: Console
Classifier: Intended Audience :: Developers
Classifier: Operating System :: OS Independent
Classifier: Topic :: Software Development :: Libraries
Classifier: Topic :: Utilities
Requires-Python: >=3.13
License-File: LICENSE
License-File: AUTHORS
Requires-Dist: hy>=1.2.0
Requires-Dist: hyrule>=1.0.1
Requires-Dist: beautifhy>=1.2.1
Requires-Dist: prompt_toolkit>=3.0.52
Dynamic: license-file
